actiontest/Number.py
actiontest/__init__.py
actiontest-0.1.0.dist-info/LICENSE
actiontest-0.1.0.dist-info/METADATA
actiontest-0.1.0.dist-info/WHEEL
actiontest-0.1.0.dist-info/top_level.txt
actiontest-0.1.0.dist-info/RECORD
