Metadata-Version: 2.1
Name: actiontest
Version: 0.1.0
Summary: actiontest PyPI (Python Package Index) Package
Home-page: https://github.com/a-shelton-test-org/actiontest
Author: Drew Shelton
Author-email: dshelts9306@gmail.com
Project-URL: Documentation, https://github.com/a-shelton-test-org/actiontest
Project-URL: Bug Reports, https://github.com/a-shelton-test-org/actiontest/issues
Project-URL: Source Code, https://github.com/a-shelton-test-org/actiontest
Keywords: actiontest,pypi,package
Classifier: Development Status :: 5 - Production/Stable
Classifier: Intended Audience :: Developers
Classifier: Topic :: Software Development :: Build Tools
Classifier: Programming Language :: Python :: 3.11
Classifier: License :: OSI Approved :: MIT License
Classifier: Operating System :: OS Independent
Requires-Python: >=3.11
License-File: LICENSE
Provides-Extra: dev
Requires-Dist: check-manifest ; extra == 'dev'
